README.md
setup.cfg
setup.py
sls/__init__.py
sls/acquisition.py
sls/client.py
sls/config.py
sls/enum36.py
sls/gui.py
sls/protocol.py
sls/save.py
sls/server.py
sls/settings.py
sls/shm.py
sls/simulator.py
sls_detector.egg-info/PKG-INFO
sls_detector.egg-info/SOURCES.txt
sls_detector.egg-info/dependency_links.txt
sls_detector.egg-info/entry_points.txt
sls_detector.egg-info/requires.txt
sls_detector.egg-info/top_level.txt
sls_detector.egg-info/zip-safe